COPYING.txt
MANIFEST.in
README.md
RELEASE-VERSION
setup.py
version.py
src/pytwain.egg-info/PKG-INFO
src/pytwain.egg-info/SOURCES.txt
src/pytwain.egg-info/dependency_links.txt
src/pytwain.egg-info/top_level.txt
src/twain/__init__.py
src/twain/exceptions.py
src/twain/utils.py
src/twain/windows.py
src/twain/lowlevel/__init__.py
src/twain/lowlevel/constants.py
src/twain/lowlevel/structs.py